display_exceptions/__init__.py
display_exceptions/exceptions.py
display_exceptions/middleware.py
display_exceptions/views.py
display_exceptions/static/exceptions/display_exception.css
display_exceptions/static/exceptions/bootstrap/css/bootstrap.min.css
display_exceptions/static/exceptions/bootstrap/fonts/glyphicons-halflings-regular.eot
display_exceptions/static/exceptions/bootstrap/fonts/glyphicons-halflings-regular.svg
display_exceptions/static/exceptions/bootstrap/fonts/glyphicons-halflings-regular.ttf
display_exceptions/static/exceptions/bootstrap/fonts/glyphicons-halflings-regular.woff
display_exceptions/static/exceptions/bootstrap/fonts/glyphicons-halflings-regular.woff2
display_exceptions/templates/exceptions/bad_request.html
display_exceptions/templates/exceptions/base.html
display_exceptions/templates/exceptions/not_found.html
display_exceptions/templates/exceptions/not_implemented.html
display_exceptions/templates/exceptions/notification.html
display_exceptions/templates/exceptions/permission_denied.html
display_exceptions/templates/exceptions/technical.html
django_display_exceptions-2.1.dist-info/LICENSE.txt
django_display_exceptions-2.1.dist-info/METADATA
django_display_exceptions-2.1.dist-info/WHEEL
django_display_exceptions-2.1.dist-info/top_level.txt
django_display_exceptions-2.1.dist-info/RECORD
