Metadata-Version: 2.1
Name: django-display-exceptions
Version: 2.1
Summary: This app can (slightly) encourage modularity and readability, as well as decrease code repetition and length, by using Exceptions to handle exceptional (non-standard) situations.
Home-page: https://github.com/mverleg/django_display_exception
Author: Mark V
Author-email: mdilligaf@gmail.com
Maintainer: (the author)
License: Revised BSD License (LICENSE.txt)
Keywords: django,coding-style
Platform: UNKNOWN
Classifier: Development Status :: 5 - Production/Stable
Classifier: Intended Audience :: Developers
Classifier: Natural Language :: English
Classifier: License :: OSI Approved :: BSD License
Classifier: Operating System :: OS Independent
Classifier: Programming Language :: Python
Classifier: Programming Language :: Python :: 2
Classifier: Programming Language :: Python :: 2.6
Classifier: Programming Language :: Python :: 2.7
Classifier: Programming Language :: Python :: 3
Classifier: Programming Language :: Python :: 3.3
Classifier: Programming Language :: Python :: 3.4
Classifier: Programming Language :: Python :: 3.5
Classifier: Programming Language :: Python :: Implementation :: PyPy
Classifier: Topic :: Software Development :: Libraries :: Python Modules
Requires-Dist: django
